DatastoreClient
