Metadata-Version: 2.1
Name: DatastoreClient
Version: 0.0.9
Summary: Python Client for Datastore APIs
Home-page: https://github.com/TaylorHere
Author: TaylorHere
Author-email: taylorherelee@gmail.com
License: UNKNOWN
Platform: UNKNOWN
Classifier: Programming Language :: Python :: 3
Classifier: License :: OSI Approved :: MIT License
